Rajveer/Rajveer.py
Rajveer/__init__.py
Rajveer-0.7.dist-info/METADATA
Rajveer-0.7.dist-info/WHEEL
Rajveer-0.7.dist-info/top_level.txt
Rajveer-0.7.dist-info/RECORD
