Metadata-Version: 2.1
Name: Rajveer
Version: 0.7
Summary: A Python API Module That Helps Python Dev
Author: Rajveer Verma
Requires-Dist: requests
Requires-Dist: user-agent
Requires-Dist: colorama
Requires-Dist: termcolor
